MANIFEST.in
README.md
setup.py
django_indonesia_regions.egg-info/PKG-INFO
django_indonesia_regions.egg-info/SOURCES.txt
django_indonesia_regions.egg-info/dependency_links.txt
django_indonesia_regions.egg-info/top_level.txt
djindonesiaregions/__init__.py
djindonesiaregions/models.py
djindonesiaregions/tests.py
djindonesiaregions/csv/districts.csv
djindonesiaregions/csv/provinces.csv
djindonesiaregions/csv/regencies.csv
djindonesiaregions/csv/villages.csv
djindonesiaregions/migrations/0001_initial.py
djindonesiaregions/migrations/__init__.py