Metadata-Version: 1.1
Name: django-indonesia-regions
Version: 1.0.5
Summary: Pluggable django providing indonesian regions model including the initial data
Home-page: https://github.com/Keda87/django-indonesia-regions
Author: Adiyat Mubarak
Author-email: adiyatmubarak@gmail.com
License: MIT License
Platform: UNKNOWN
Classifier: Environment :: Web Environment
Classifier: Framework :: Django
Classifier: Intended Audience :: Developers
Classifier: License :: OSI Approved :: BSD License
Classifier: Operating System :: OS Independent
Classifier: Programming Language :: Python
Classifier: Programming Language :: Python :: 2.7
Classifier: Programming Language :: Python :: 3
Classifier: Programming Language :: Python :: 3.4
Classifier: Programming Language :: Python :: 3.5
